LICENSE.txt
MANIFEST.in
README.rst
setup.cfg
setup.py
version.py
nb2md/__init__.py
nb2md/nb2md.py
nb2md/version.py
nb2md.egg-info/PKG-INFO
nb2md.egg-info/SOURCES.txt
nb2md.egg-info/dependency_links.txt
nb2md.egg-info/entry_points.txt
nb2md.egg-info/requires.txt
nb2md.egg-info/top_level.txt