Metadata-Version: 1.2
Name: nb2md
Version: 0.0.25
Summary: Conversion of Jupyter and Zeppelin notebooks to Jupyter or Markdown formats
Home-page: https://github.com/elehcimd/nb2md
Author: Michele Dallachiesa
Author-email: michele.dallachiesa@minodes.com
License: MIT
Platform: UNKNOWN
Classifier: Development Status :: 3 - Alpha
Classifier: Intended Audience :: Developers
Classifier: Intended Audience :: Science/Research
Classifier: Intended Audience :: System Administrators
Classifier: License :: OSI Approved :: MIT License
Classifier: Programming Language :: Python :: 3
Requires-Python: >=3.4
